{
  "project_info": {
    "project_number": "164518155951",
    "project_id": "pet-adoption-112",
    "storage_bucket": "pet-adoption-112.firebasestorage.app"
  },
  "client": [
    {
      "client_info": {
        "mobilesdk_app_id": "1:164518155951:android:ab3731390f94d9bbd3265a",
        "android_client_info": {
          "package_name": "com.example.pet_adoption"
        }
      },
      "oauth_client": [],
      "api_key": [
        {
          "current_key": "AIzaSyCbECzFsGH5TzKmGWrmQRK_6_Q4XeLRgv4"
        }
      ],
      "services": {
        "appinvite_service": {
          "other_platform_oauth_client": []
        }
      }
    }
  ],
  "configuration_version": "1"
}